pythonanywhereapiclient/client.py
pythonanywhereapiclient/config.py
pythonanywhereapiclient/console.py
pythonanywhereapiclient/error.py
pythonanywhereapiclient/file.py
pythonanywhereapiclient/schedule.py
pythonanywhereapiclient/utils.py
pythonanywhereapiclient/webapp.py
tests/console/conftest.py
tests/console/test_console.py
tests/file/conftest.py
tests/file/test_file.py
tests/schedule/conftest.py
tests/schedule/test_schedule.py
tests/webapp/conftest.py
tests/webapp/test_webapp.py
pythonanywhereapiclient-2.0.1.dist-info/LICENSE
pythonanywhereapiclient-2.0.1.dist-info/METADATA
pythonanywhereapiclient-2.0.1.dist-info/WHEEL
pythonanywhereapiclient-2.0.1.dist-info/top_level.txt
pythonanywhereapiclient-2.0.1.dist-info/RECORD
