Metadata-Version: 2.1
Name: pythonanywhereapiclient
Version: 2.0.1
Summary: Thin wrapper for the PythonAnywhere API.
Home-page: https://gitlab.com/texperience/pythonanywhereapiclient
Author: Timo Rieber
Author-email: trieber@texperience.de
License: MIT License (MIT)
Platform: UNKNOWN
Classifier: Development Status :: 5 - Production/Stable
Classifier: Environment :: Web Environment
Classifier: Intended Audience :: Developers
Classifier: License :: OSI Approved :: MIT License
Classifier: Operating System :: OS Independent
Classifier: Programming Language :: Python
Classifier: Programming Language :: Python :: 3
Classifier: Programming Language :: Python :: 3.7
Classifier: Programming Language :: Python :: 3.8
Classifier: Programming Language :: Python :: 3.9
Classifier: Topic :: Internet :: WWW/HTTP
Classifier: Topic :: Software Development
Requires-Dist: requests (<3.0,>=2.23)
Provides-Extra: linting
Requires-Dist: brunette (<1.0,>=0.2.0) ; extra == 'linting'
Requires-Dist: flake8 (<4.0,>=3.7) ; extra == 'linting'
Requires-Dist: isort (<6.0,>=5.7) ; extra == 'linting'
Provides-Extra: testing
Requires-Dist: coverage (<6.0,>=5.0) ; extra == 'testing'
Requires-Dist: pytest (<6.0,>=5.3) ; extra == 'testing'
Requires-Dist: responses (<1.0,>=0.10) ; extra == 'testing'
Requires-Dist: tox (<4.0,>=3.14) ; extra == 'testing'
